ogsdownloader/__init__.py
ogsdownloader/__main__.py
ogsdownloader/exceptions.py
ogsdownloader/game.py
ogsdownloader/oauth2.py
ogsdownloader/player.py
ogsdownloader-0.1.0.dist-info/AUTHORS
ogsdownloader-0.1.0.dist-info/METADATA
ogsdownloader-0.1.0.dist-info/WHEEL
ogsdownloader-0.1.0.dist-info/top_level.txt
ogsdownloader-0.1.0.dist-info/RECORD
