Metadata-Version: 2.1
Name: ogsdownloader
Version: 0.1.0
Summary: UNKNOWN
Home-page: UNKNOWN
Author: Serene-Arc
Author-email: serenical@gmail.com
License: UNKNOWN
Platform: UNKNOWN
License-File: AUTHORS
Requires-Dist: appdirs
Requires-Dist: requests
